setup.cfg
setup.py
litesockets/__init__.py
litesockets/client.py
litesockets/server.py
litesockets/socketexecuter.py
litesockets/stats.py
litesockets/tcp.py
litesockets/udp.py
litesockets.egg-info/PKG-INFO
litesockets.egg-info/SOURCES.txt
litesockets.egg-info/dependency_links.txt
litesockets.egg-info/requires.txt
litesockets.egg-info/top_level.txt