Metadata-Version: 1.1
Name: litesockets
Version: 0.7.1
Summary: A multi threaded socket library for python
Home-page: https://github.com/lwahlmeier/python-litesockets
Author: Luke Wahlmeier
Author-email: lwahlmeier@gmail.com
License: unlicense
Download-URL: https://github.com/lwahlmeier/python-litesockets/tarball/0.7.1
Keywords: networking
Platform: UNKNOWN
Classifier: Development Status :: 4 - Beta
Classifier: Intended Audience :: Developers
Classifier: Natural Language :: English
Classifier: Operating System :: POSIX :: Linux
Classifier: Programming Language :: Python
Classifier: Topic :: Software Development :: Libraries
Classifier: Topic :: Utilities
Classifier: License :: Public Domain
